{
  "date": "2025-12-08",
  "collected_at": "2025-12-08T01:40:23.905Z",
  "target_date": "2025-12-09",
  "city": "서울",
  "predictions": {
    "openweather": {
      "error": "Failed to switch provider: OpenWeatherMap API key is required when not using proxy",
      "collected_at": "2025-12-08T01:40:23.905Z"
    },
    "weatherapi": {
      "error": "Failed to switch provider: WeatherAPIAdapter requires API key in configuration",
      "collected_at": "2025-12-08T01:40:23.905Z"
    },
    "openmeteo": {
      "temp_max": 6.1,
      "temp_min": -3.2,
      "temp_day": 1.4499999999999997,
      "temp_night": -3.2,
      "condition_main": "대체로 맑음",
      "condition_description": "대체로 맑음",
      "condition_description_ko": "대체로 맑음",
      "condition_icon": "01d",
      "humidity": 0,
      "wind_speed": 1.5555555555555554,
      "precipitation_probability": 0,
      "predicted_at": "2025-12-08T01:40:24.437Z"
    }
  }
}