{
  "date": "2026-02-22",
  "collected_at": "2026-02-22T02:08:38.409Z",
  "target_date": "2026-02-23",
  "city": "서울",
  "predictions": {
    "openweather": {
      "error": "Failed to switch provider: OpenWeatherMap API key is required when not using proxy",
      "collected_at": "2026-02-22T02:08:38.409Z"
    },
    "weatherapi": {
      "error": "Failed to switch provider: WeatherAPIAdapter requires API key in configuration",
      "collected_at": "2026-02-22T02:08:38.409Z"
    },
    "openmeteo": {
      "temp_max": 1.9,
      "temp_min": -3.4,
      "temp_day": -0.75,
      "temp_night": -3.4,
      "condition_main": "흐림",
      "condition_description": "흐림",
      "condition_description_ko": "흐림",
      "condition_icon": "03d",
      "humidity": 0,
      "wind_speed": 2.861111111111111,
      "precipitation_probability": 0,
      "predicted_at": "2026-02-22T02:08:39.143Z"
    }
  }
}